{
    "/app.js": "/app.js",
    "/app.css": "/app.css",
    "/contentBox.js": "/contentBox.js",
    "/embedTemplate.js": "/embedTemplate.js",
    "/image-block.js": "/image-block.js",
    "/imageBlock.js": "/imageBlock.js",
    "/imageGallery.js": "/imageGallery.js",
    "/linkDropdown.js": "/linkDropdown.js",
    "/newsletter.js": "/newsletter.js",
    "/search-filters.js": "/search-filters.js",
    "/teamBlock.js": "/teamBlock.js",
    "/teamMember.js": "/teamMember.js",
    "/tooltip.js": "/tooltip.js",
    "/videoGallery.js": "/videoGallery.js"
}
